requisitor/__init__.py
requisitor/auth.py
requisitor/codes.py
requisitor/errors.py
requisitor/handlers.py
requisitor/headers.py
requisitor/multipart.py
requisitor/response.py
requisitor/sentinel.py
requisitor/session.py
requisitor/utils.py
requisitor-0.0.2.dist-info/LICENSE
requisitor-0.0.2.dist-info/METADATA
requisitor-0.0.2.dist-info/WHEEL
requisitor-0.0.2.dist-info/top_level.txt
requisitor-0.0.2.dist-info/RECORD
